bytedabtestmonitor/__init__.py
bytedabtestmonitor-0.0.1.dist-info/METADATA
bytedabtestmonitor-0.0.1.dist-info/WHEEL
bytedabtestmonitor-0.0.1.dist-info/top_level.txt
bytedabtestmonitor-0.0.1.dist-info/RECORD
